payplus/__init__.py
payplus/admin.py
payplus/apps.py
payplus/enum.py
payplus/models.py
payplus/momopay.py
payplus/serializer.py
payplus/tests.py
payplus/urls.py
payplus/views.py
payplus/migrations/0001_initial.py
payplus/migrations/__init__.py
djangopayplus-1.2.5.dist-info/LICENSE
djangopayplus-1.2.5.dist-info/METADATA
djangopayplus-1.2.5.dist-info/WHEEL
djangopayplus-1.2.5.dist-info/top_level.txt
djangopayplus-1.2.5.dist-info/RECORD
