Metadata-Version: 2.1
Name: djangopayplus
Version: 1.2.5
Summary: A momo payment package
Home-page: https://github.com/pypa/sampleproject
Author: Anthony Mensah Addae
Author-email: maaddae.co@gmail.com
License: UNKNOWN
Platform: UNKNOWN
Classifier: Programming Language :: Python :: 3
Classifier: License :: OSI Approved :: MIT License
Classifier: Operating System :: OS Independent
Requires-Python: >=3.6
License-File: LICENSE
